{
  "TransactionID": {
    "type": "string",
    "required": true,
    "description": "Inferred type: string. Nulls detected: 0"
  },
  "AccountID": {
    "type": "string",
    "required": false,
    "description": "Inferred type: string. Nulls detected: 1"
  },
  "TransactionAmount": {
    "type": "float",
    "required": false,
    "description": "Inferred type: string. Nulls detected: 1"
  },
  "TransactionDate": {
    "type": "datetime",
    "required": false,
    "description": "Inferred type: string. Nulls detected: 2"
  },
  "TransactionType": {
    "type": "string",
    "required": false,
    "description": "Inferred type: string. Nulls detected: 1"
  },
  "Location": {
    "type": "string",
    "required": false,
    "description": "Inferred type: string. Nulls detected: 1"
  },
  "AccountBalance": {
    "type": "float",
    "required": false,
    "description": "Inferred type: string. Nulls detected: 1"
  }
}